thirdweb_eth_account/__init__.py
thirdweb_eth_account/account.py
thirdweb_eth_account/datastructures.py
thirdweb_eth_account/messages.py
thirdweb_eth_account/py.typed
thirdweb_eth_account/_utils/__init__.py
thirdweb_eth_account/_utils/legacy_transactions.py
thirdweb_eth_account/_utils/signing.py
thirdweb_eth_account/_utils/transaction_utils.py
thirdweb_eth_account/_utils/typed_transactions.py
thirdweb_eth_account/_utils/validation.py
thirdweb_eth_account/_utils/structured_data/__init__.py
thirdweb_eth_account/_utils/structured_data/hashing.py
thirdweb_eth_account/_utils/structured_data/validation.py
thirdweb_eth_account/hdaccount/__init__.py
thirdweb_eth_account/hdaccount/_utils.py
thirdweb_eth_account/hdaccount/deterministic.py
thirdweb_eth_account/hdaccount/mnemonic.py
thirdweb_eth_account/hdaccount/wordlist/chinese_simplified.txt
thirdweb_eth_account/hdaccount/wordlist/chinese_traditional.txt
thirdweb_eth_account/hdaccount/wordlist/czech.txt
thirdweb_eth_account/hdaccount/wordlist/english.txt
thirdweb_eth_account/hdaccount/wordlist/french.txt
thirdweb_eth_account/hdaccount/wordlist/italian.txt
thirdweb_eth_account/hdaccount/wordlist/japanese.txt
thirdweb_eth_account/hdaccount/wordlist/korean.txt
thirdweb_eth_account/hdaccount/wordlist/spanish.txt
thirdweb_eth_account/signers/__init__.py
thirdweb_eth_account/signers/base.py
thirdweb_eth_account/signers/local.py
thirdweb_eth_account-0.6.6.dist-info/LICENSE
thirdweb_eth_account-0.6.6.dist-info/METADATA
thirdweb_eth_account-0.6.6.dist-info/WHEEL
thirdweb_eth_account-0.6.6.dist-info/top_level.txt
thirdweb_eth_account-0.6.6.dist-info/RECORD
