Metadata-Version: 2.1
Name: thirdweb-eth-account
Version: 0.6.6
Summary: eth-account: Sign Ethereum transactions and messages with local private keys
Home-page: https://github.com/ethereum/eth-account
Author: The Ethereum Foundation
Author-email: snakecharmers@ethereum.org
License: MIT
Keywords: ethereum
Platform: UNKNOWN
Classifier: Development Status :: 3 - Alpha
Classifier: Intended Audience :: Developers
Classifier: License :: OSI Approved :: MIT License
Classifier: Natural Language :: English
Classifier: Operating System :: MacOS
Classifier: Operating System :: POSIX
Classifier: Programming Language :: Python :: 3
Classifier: Programming Language :: Python :: 3.7
Classifier: Programming Language :: Python :: 3.8
Classifier: Programming Language :: Python :: 3.9
Classifier: Programming Language :: Python :: 3.10
Requires-Python: >=3.6, <4
Provides-Extra: test
Provides-Extra: lint
Provides-Extra: doc
Provides-Extra: dev
License-File: LICENSE
